MANIFEST.in
README.rst
requirements.txt
setup.py
Dropbox_Backup.egg-info/SOURCES.txt
bin/dropbox_backup
dropbox_backup/__init__.py
dropbox_backup/settings.py
dropbox_backup/utils.py
dropbox_backup.egg-info/PKG-INFO
dropbox_backup.egg-info/SOURCES.txt
dropbox_backup.egg-info/dependency_links.txt
dropbox_backup.egg-info/not-zip-safe
dropbox_backup.egg-info/requires.txt
dropbox_backup.egg-info/top_level.txt