Metadata-Version: 1.0
Name: dropbox-backup
Version: 0.1.5
Summary: Create backup from your server and send them to dropbox
Home-page: http://dropbox-backup.org
Author: Thomas Kliszowski
Author-email: thomas.kliszowski@gmail.com
License: MIT
Keywords: dropbox backup upload
Platform: UNKNOWN
